README.md
setup.py
drf_dx_datagrid/__init__.py
drf_dx_datagrid/filters.py
drf_dx_datagrid/mixins.py
drf_dx_datagrid/pagination.py
drf_dx_datagrid/summary.py
drf_dx_datagrid/viewsets.py
drf_dx_datagrid.egg-info/PKG-INFO
drf_dx_datagrid.egg-info/SOURCES.txt
drf_dx_datagrid.egg-info/dependency_links.txt
drf_dx_datagrid.egg-info/requires.txt
drf_dx_datagrid.egg-info/top_level.txt