Metadata-Version: 2.1
Name: drf-dx-datagrid
Version: 0.2.1
Summary: This package provides easy integration between Django REST framework and DevExtreme Data Grid. It handles grouping, paging, filtering, aggregating and ordering on serverside.
Home-page: https://github.com/SergeyMatveev88/drf-dx-datagrid
Author: SergeyMatveev88
Author-email: dazranagon@yandex.ru
License: MIT
Platform: UNKNOWN
Classifier: Programming Language :: Python :: 3
Classifier: License :: OSI Approved :: MIT License
Classifier: Operating System :: OS Independent
Classifier: Framework :: Django
Requires-Python: >=3.5
